evopy/__init__.py
evopy/evopy.py
evopy/individual.py
evopy/progress_report.py
evopy/strategy.py
evopy/utils/__init__.py
evopy/utils/random.py
evopy-0.3.dist-info/LICENSE
evopy-0.3.dist-info/METADATA
evopy-0.3.dist-info/WHEEL
evopy-0.3.dist-info/top_level.txt
evopy-0.3.dist-info/RECORD
