Metadata-Version: 2.1
Name: evopy
Version: 0.3
Summary: Evolutionary Strategies made simple
Home-page: http://github.com/evopy/evopy
Author: evopy
Author-email: info@gandreadis.com
License: MIT
Platform: UNKNOWN
Classifier: Programming Language :: Python :: 3
Classifier: License :: OSI Approved :: MIT License
Classifier: Operating System :: OS Independent
Requires-Dist: numpy
